py_mysql_connector_python-1.1.3.dist-info/licenses/LICENSE
pymysql/__init__.py
pymysql/_auth.py
pymysql/charset.py
pymysql/connections.py
pymysql/converters.py
pymysql/cursors.py
pymysql/err.py
pymysql/optionfile.py
pymysql/protocol.py
pymysql/times.py
pymysql/constants/CLIENT.py
pymysql/constants/COMMAND.py
pymysql/constants/CR.py
pymysql/constants/ER.py
pymysql/constants/FIELD_TYPE.py
pymysql/constants/FLAG.py
pymysql/constants/SERVER_STATUS.py
pymysql/constants/__init__.py
pymysql/constants/examples/__init__.py
pymysql/constants/examples/main.py
pymysql/constants/examples/settings.py
pymysql/constants/examples/setup.py
pymysql/constants/examples/db/__init__.py
pymysql/constants/examples/db/helpers.py
pymysql/constants/examples/db/mig.sql
pymysql/constants/examples/db/mysql_connection.py
pymysql/constants/examples/images/__init__.py
pymysql/constants/examples/images/logo.png
pymysql/constants/examples/interface/__init__.py
pymysql/constants/examples/interface/auth_window_ui.py
pymysql/constants/examples/interface/auth_window_ui.ui
pymysql/constants/examples/interface/table_window_ui.py
pymysql/constants/examples/interface/table_window_ui.ui
pymysql/constants/examples/interface/user_window_ui.py
pymysql/constants/examples/interface/user_window_ui.ui
pymysql/constants/examples/windows/__init__.py
pymysql/constants/examples/windows/add_row_dialog.py
pymysql/constants/examples/windows/auth_window.py
pymysql/constants/examples/windows/table_window.py
pymysql/constants/examples/windows/user_window.py
py_mysql_connector_python-1.1.3.dist-info/METADATA
py_mysql_connector_python-1.1.3.dist-info/WHEEL
py_mysql_connector_python-1.1.3.dist-info/top_level.txt
py_mysql_connector_python-1.1.3.dist-info/RECORD
